plotis/__init__.py
plotis/plotis.py
plotis-0.1.9.dist-info/METADATA
plotis-0.1.9.dist-info/WHEEL
plotis-0.1.9.dist-info/licenses/LICENCE
plotis-0.1.9.dist-info/RECORD
