Metadata-Version: 2.3
Name: plotis
Version: 0.1.9
Summary: Plot isolation tool for python
Project-URL: Homepage, https://github.com/victorbrun/plotis
Project-URL: Issues, https://github.com/victorbrun/plotis/issues
Author-email: Victor Brun <me@victorbrun.com>
License-File: LICENCE
Classifier: License :: OSI Approved :: BSD License
Classifier: Operating System :: OS Independent
Classifier: Programming Language :: Python :: 3
Requires-Python: >=3.9
Requires-Dist: matplotlib
Requires-Dist: numpy
Requires-Dist: pandas
